{"name":"t:sections.footer.name","type":"footer","sections":{"newsletter":{"type":"newsletter","blocks":{"heading":{"type":"heading","settings":{"heading":"<a href=\"\/pages\/contact\" target=\"_blank\" title=\"Contact\">contact us<\/a>","heading_size":"h1"}},"paragraph":{"type":"paragraph","settings":{"text":"<h2><strong>looking for b2b contractors<\/strong><\/h2>"}},"email-form":{"type":"email_form","disabled":true,"settings":{}}},"block_order":["heading","paragraph","email-form"],"disabled":true,"settings":{"color_scheme":"scheme-4","full_width":true,"padding_top":40,"padding_bottom":56}},"footer":{"type":"footer","settings":{"color_scheme":"scheme-2","newsletter_enable":false,"newsletter_heading":"","enable_follow_on_shop":false,"show_social":true,"enable_country_selector":true,"enable_language_selector":true,"payment_enable":true,"show_policy":false,"margin_top":0,"padding_top":44,"padding_bottom":40}}},"order":["newsletter","footer"]}